{
  "schema_version": "market-data-v2",
  "generated_at": "2026-07-24 20:55:40 CST",
  "generated_timezone": "Asia/Taipei",
  "market_mode": "full",
  "privacy_note": "This file contains market data only. No personal holdings, cash, target allocation, or buy/sell recommendations are included.",
  "taiwan": {
    "source": "FinMind",
    "mode": "tw_intraday_or_latest_available",
    "lookback_start": "2026-04-25",
    "lookback_end": "2026-07-24",
    "market_margin": {
      "date": "2026-07-24",
      "today_balance": 577059537000,
      "yesterday_balance": 582626349000,
      "delta": -5566812000,
      "freshness": "fresh"
    },
    "stocks": {
      "0050": {
        "name": "元大台灣50",
        "price_date": "2026-07-24",
        "open": 102.55,
        "max": 103.05,
        "min": 101.3,
        "close": 101.7,
        "spread": -2.2,
        "trading_volume": 105138918,
        "institutional_date": "2026-07-24",
        "foreign_investor_buy_sell": -37393633,
        "investment_trust_buy_sell": 1000000,
        "dealer_self_buy_sell": 5874426,
        "dealer_hedging_buy_sell": -5754856,
        "margin_date": "2026-07-23",
        "margin_today_balance": 48790,
        "margin_delta_estimated": -103,
        "technical": {
          "pct_change_5d": 1.5476784822765932,
          "pct_change_20d": -5.1305970149253755,
          "high_60d": 111.15,
          "low_60d": 90.5,
          "pct_from_60d_high": -8.502024291497978,
          "pct_from_60d_low": 12.375690607734802
        },
        "freshness": {
          "price": "fresh",
          "institutional": "fresh",
          "margin": "fresh"
        }
      },
      "00988A": {
        "name": "主動統一台股增長",
        "price_date": "2026-07-24",
        "open": 17.48,
        "max": 17.53,
        "min": 17.1,
        "close": 17.22,
        "spread": -0.64,
        "trading_volume": 40104828,
        "institutional_date": "2026-07-24",
        "foreign_investor_buy_sell": -4859261,
        "investment_trust_buy_sell": 0,
        "dealer_self_buy_sell": 0,
        "dealer_hedging_buy_sell": -4499950,
        "margin_date": "2026-07-24",
        "margin_today_balance": 71345,
        "margin_delta_estimated": -1019,
        "technical": {
          "pct_change_5d": 6.034482758620685,
          "pct_change_20d": -25.35760728218466,
          "high_60d": 23.73,
          "low_60d": 16.24,
          "pct_from_60d_high": -27.43362831858408,
          "pct_from_60d_low": 6.034482758620685
        },
        "freshness": {
          "price": "fresh",
          "institutional": "fresh",
          "margin": "fresh"
        }
      },
      "6005": {
        "name": "群益證",
        "price_date": "2026-07-24",
        "open": 34.35,
        "max": 35.05,
        "min": 34.25,
        "close": 34.8,
        "spread": 0.35,
        "trading_volume": 6712949,
        "institutional_date": "2026-07-24",
        "foreign_investor_buy_sell": 190002,
        "investment_trust_buy_sell": 16000,
        "dealer_self_buy_sell": 0,
        "dealer_hedging_buy_sell": 0,
        "margin_date": "2026-07-23",
        "margin_today_balance": 5152,
        "margin_delta_estimated": 58,
        "technical": {
          "pct_change_5d": 5.454545454545445,
          "pct_change_20d": -10.309278350515461,
          "high_60d": 45.05,
          "low_60d": 28.05,
          "pct_from_60d_high": -22.752497225305213,
          "pct_from_60d_low": 24.064171122994637
        },
        "freshness": {
          "price": "fresh",
          "institutional": "fresh",
          "margin": "fresh"
        }
      }
    }
  },
  "us": {
    "source": "Yahoo Finance via yfinance",
    "mode": "us_intraday_or_latest_available",
    "tickers": {
      "SPY": {
        "date": "2026-07-23",
        "open": 739.3699951171875,
        "high": 742.5599975585938,
        "low": 735.2100219726562,
        "close": 738.1799926757812,
        "previous_close": 747.4099731445312,
        "pct_change": -1.2349287272575782,
        "volume": 55370700.0,
        "intraday_or_latest_price": 738.1799926757812,
        "intraday_vs_previous_close_pct": -1.2349287272575782,
        "technical": {
          "pct_change_5d": -1.6703935577468076,
          "pct_change_20d": 0.673722452021086,
          "high_52w": 760.4000244140625,
          "low_52w": 619.2899780273438,
          "pct_from_52w_high": -2.922150318893435,
          "pct_from_52w_low": 19.197794065252594
        },
        "freshness": "fresh"
      },
      "QQQ": {
        "date": "2026-07-23",
        "open": 694.6699829101562,
        "high": 698.6599731445312,
        "low": 687.7899780273438,
        "close": 691.9600219726562,
        "previous_close": 705.3499755859375,
        "pct_change": -1.898341826999872,
        "volume": 43695900.0,
        "intraday_or_latest_price": 691.9600219726562,
        "intraday_vs_previous_close_pct": -1.898341826999872,
        "technical": {
          "pct_change_5d": -1.980335498824537,
          "pct_change_20d": -2.625872234492088,
          "high_52w": 748.6500244140625,
          "low_52w": 551.6799926757812,
          "pct_from_52w_high": -7.5722968800776,
          "pct_from_52w_low": 25.427789870805896
        },
        "freshness": "fresh"
      },
      "^IXIC": {
        "date": "2026-07-23",
        "open": 25245.5390625,
        "high": 25358.279296875,
        "low": 24954.76953125,
        "close": 25137.689453125,
        "previous_close": 25690.900390625,
        "pct_change": -2.153334173145116,
        "volume": 7655810000.0,
        "intraday_or_latest_price": 25137.689453125,
        "intraday_vs_previous_close_pct": -2.153334173145116,
        "technical": {
          "pct_change_5d": -2.8755939490284876,
          "pct_change_20d": -1.330439035758857,
          "high_52w": 27190.2109375,
          "low_52w": 20560.169921875,
          "pct_from_52w_high": -7.548751604365888,
          "pct_from_52w_low": 22.264016049691037
        },
        "freshness": "fresh"
      },
      "SOXX": {
        "date": "2026-07-23",
        "open": 545.5,
        "high": 558.0900268554688,
        "low": 543.7899780273438,
        "close": 551.239990234375,
        "previous_close": 555.52001953125,
        "pct_change": -0.7704545554427567,
        "volume": 6646200.0,
        "intraday_or_latest_price": 551.239990234375,
        "intraday_vs_previous_close_pct": -0.7704545554427567,
        "technical": {
          "pct_change_5d": 3.909517480560787,
          "pct_change_20d": -8.355778847152951,
          "high_52w": 655.9500122070312,
          "low_52w": 232.3300018310547,
          "pct_from_52w_high": -15.963109996803782,
          "pct_from_52w_low": 137.26595183140606
        },
        "freshness": "fresh"
      },
      "SMH": {
        "date": "2026-07-23",
        "open": 577.2000122070312,
        "high": 586.8900146484375,
        "low": 574.0,
        "close": 580.1699829101562,
        "previous_close": 586.9099731445312,
        "pct_change": -1.1483857052664526,
        "volume": 7907500.0,
        "intraday_or_latest_price": 580.1699829101562,
        "intraday_vs_previous_close_pct": -1.1483857052664526,
        "technical": {
          "pct_change_5d": 1.9774309811467106,
          "pct_change_20d": -6.260906267365584,
          "high_52w": 671.8300170898438,
          "low_52w": 279.19000244140625,
          "pct_from_52w_high": -13.643337131128785,
          "pct_from_52w_low": 107.80471286106201
        },
        "freshness": "fresh"
      },
      "^VIX": {
        "date": "2026-07-24",
        "open": 18.959999084472656,
        "high": 19.049999237060547,
        "low": 18.520000457763672,
        "close": 18.690000534057617,
        "previous_close": 18.700000762939453,
        "pct_change": -0.05347715761410132,
        "volume": 0.0,
        "intraday_or_latest_price": 18.690000534057617,
        "intraday_vs_previous_close_pct": -0.05347715761410132,
        "technical": {
          "pct_change_5d": -0.4262116236282032,
          "pct_change_20d": -1.0587552252670718,
          "high_52w": 35.29999923706055,
          "low_52w": 13.380000114440918,
          "pct_from_52w_high": -47.05382170536856,
          "pct_from_52w_low": 39.686101451416754
        },
        "freshness": "fresh"
      },
      "NVDA": {
        "date": "2026-07-23",
        "open": 209.4600067138672,
        "high": 210.8699951171875,
        "low": 205.9600067138672,
        "close": 208.75999450683594,
        "previous_close": 212.05999755859375,
        "pct_change": -1.556164807012217,
        "volume": 110250900.0,
        "intraday_or_latest_price": 208.75999450683594,
        "intraday_vs_previous_close_pct": -1.556164807012217,
        "technical": {
          "pct_change_5d": 0.6557380185027162,
          "pct_change_20d": 4.904519852681366,
          "high_52w": 236.5399932861328,
          "low_52w": 164.07000732421875,
          "pct_from_52w_high": -11.744313675401408,
          "pct_from_52w_low": 27.23836483672808
        },
        "freshness": "fresh"
      },
      "TSM": {
        "date": "2026-07-23",
        "open": 415.8399963378906,
        "high": 420.8399963378906,
        "low": 411.79998779296875,
        "close": 415.5799865722656,
        "previous_close": 421.2099914550781,
        "pct_change": -1.3366266225935286,
        "volume": 11025400.0,
        "intraday_or_latest_price": 415.5799865722656,
        "intraday_vs_previous_close_pct": -1.3366266225935286,
        "technical": {
          "pct_change_5d": 1.4252932291402898,
          "pct_change_20d": -5.7278317648794435,
          "high_52w": 479.0,
          "low_52w": 223.6999969482422,
          "pct_from_52w_high": -13.240086310591725,
          "pct_from_52w_low": 85.77558884295335
        },
        "freshness": "fresh"
      },
      "AVGO": {
        "date": "2026-07-23",
        "open": 392.19000244140625,
        "high": 397.6099853515625,
        "low": 386.82000732421875,
        "close": 392.4700012207031,
        "previous_close": 396.80999755859375,
        "pct_change": -1.0937215202723727,
        "volume": 16321900.0,
        "intraday_or_latest_price": 392.4700012207031,
        "intraday_vs_previous_close_pct": -1.0937215202723727,
        "technical": {
          "pct_change_5d": 4.8123884166703546,
          "pct_change_20d": 2.7220126409082557,
          "high_52w": 495.0,
          "low_52w": 281.6099853515625,
          "pct_from_52w_high": -20.713131066524625,
          "pct_from_52w_low": 39.3665074520503
        },
        "freshness": "fresh"
      },
      "MSFT": {
        "date": "2026-07-23",
        "open": 389.9700012207031,
        "high": 391.7799987792969,
        "low": 377.3900146484375,
        "close": 381.5799865722656,
        "previous_close": 390.3399963378906,
        "pct_change": -2.2441998892785864,
        "volume": 30301300.0,
        "intraday_or_latest_price": 381.5799865722656,
        "intraday_vs_previous_close_pct": -2.2441998892785864,
        "technical": {
          "pct_change_5d": -4.8666215991560735,
          "pct_change_20d": 4.4108782066693,
          "high_52w": 555.4500122070312,
          "low_52w": 349.20001220703125,
          "pct_from_52w_high": -31.302551411225743,
          "pct_from_52w_low": 9.272615473460277
        },
        "freshness": "fresh"
      },
      "GOOGL": {
        "date": "2026-07-23",
        "open": 321.1300048828125,
        "high": 324.489990234375,
        "low": 314.8999938964844,
        "close": 317.69000244140625,
        "previous_close": 342.0899963378906,
        "pct_change": -7.13262420932762,
        "volume": 69186700.0,
        "intraday_or_latest_price": 317.69000244140625,
        "intraday_vs_previous_close_pct": -7.13262420932762,
        "technical": {
          "pct_change_5d": -10.373523077380042,
          "pct_change_20d": -7.9932825800040135,
          "high_52w": 408.6099853515625,
          "low_52w": 187.82000732421875,
          "pct_from_52w_high": -22.251042845154632,
          "pct_from_52w_low": 69.14598554615283
        },
        "freshness": "fresh"
      },
      "META": {
        "date": "2026-07-23",
        "open": 608.4099731445312,
        "high": 614.6500244140625,
        "low": 597.219970703125,
        "close": 606.0999755859375,
        "previous_close": 627.1699829101562,
        "pct_change": -3.3595369514419327,
        "volume": 15472000.0,
        "intraday_or_latest_price": 606.0999755859375,
        "intraday_vs_previous_close_pct": -3.3595369514419327,
        "technical": {
          "pct_change_5d": -8.794053687316561,
          "pct_change_20d": 8.684346326666748,
          "high_52w": 796.25,
          "low_52w": 520.260009765625,
          "pct_from_52w_high": -23.880693803963894,
          "pct_from_52w_low": 16.499435706961798
        },
        "freshness": "fresh"
      },
      "AMZN": {
        "date": "2026-07-23",
        "open": 236.25999450683594,
        "high": 238.35000610351562,
        "low": 232.0500030517578,
        "close": 233.66000366210938,
        "previous_close": 244.85000610351562,
        "pct_change": -4.570145869906749,
        "volume": 47411600.0,
        "intraday_or_latest_price": 233.66000366210938,
        "intraday_vs_previous_close_pct": -4.570145869906749,
        "technical": {
          "pct_change_5d": -6.49485604353136,
          "pct_change_20d": -0.2603835741779914,
          "high_52w": 278.55999755859375,
          "low_52w": 196.0,
          "pct_from_52w_high": -16.11860794443031,
          "pct_from_52w_low": 19.214287582708867
        },
        "freshness": "fresh"
      },
      "AMBA": {
        "date": "2026-07-23",
        "open": 67.33999633789062,
        "high": 70.66999816894531,
        "low": 66.16000366210938,
        "close": 70.51000213623047,
        "previous_close": 69.01000213623047,
        "pct_change": 2.173597961986573,
        "volume": 1540300.0,
        "intraday_or_latest_price": 70.51000213623047,
        "intraday_vs_previous_close_pct": 2.173597961986573,
        "technical": {
          "pct_change_5d": 11.40780710422109,
          "pct_change_20d": 11.938403329705572,
          "high_52w": 96.69000244140625,
          "low_52w": 48.29999923706055,
          "pct_from_52w_high": -27.076222612612668,
          "pct_from_52w_low": 45.98344358177175
        },
        "freshness": "fresh"
      }
    }
  }
}