{
  "schema_version": "market-data-v2",
  "generated_at": "2026-06-30 00:31:57 CST",
  "generated_timezone": "Asia/Taipei",
  "market_mode": "us_intraday",
  "privacy_note": "This file contains market data only. No personal holdings, cash, target allocation, or buy/sell recommendations are included.",
  "taiwan": {
    "source": "FinMind",
    "mode": "tw_intraday_or_latest_available",
    "lookback_start": "2026-04-01",
    "lookback_end": "2026-06-30",
    "market_margin": {
      "date": "2026-06-29",
      "today_balance": 594229687000,
      "yesterday_balance": 590926517000,
      "delta": 3303170000,
      "freshness": "fresh"
    },
    "stocks": {
      "0050": {
        "name": "元大台灣50",
        "price_date": "2026-06-29",
        "open": 103.35,
        "max": 105.35,
        "min": 103.3,
        "close": 104.45,
        "spread": 1.35,
        "trading_volume": 106661221,
        "institutional_date": "2026-06-29",
        "foreign_investor_buy_sell": -21649761,
        "investment_trust_buy_sell": 6270000,
        "dealer_self_buy_sell": 1325005,
        "dealer_hedging_buy_sell": -3644637,
        "margin_date": "2026-06-29",
        "margin_today_balance": 13117,
        "margin_delta_estimated": 14,
        "technical": {
          "pct_change_5d": -6.027890238416555,
          "pct_change_20d": -0.9013282732447836,
          "high_60d": 111.15,
          "low_60d": 73.95,
          "pct_from_60d_high": -6.027890238416555,
          "pct_from_60d_low": 41.24408384043272
        },
        "freshness": {
          "price": "fresh",
          "institutional": "fresh",
          "margin": "fresh"
        }
      },
      "00988A": {
        "name": "主動統一台股增長",
        "price_date": "2026-06-29",
        "open": 21.85,
        "max": 21.93,
        "min": 21.3,
        "close": 21.45,
        "spread": -0.47,
        "trading_volume": 100802017,
        "institutional_date": "2026-06-29",
        "foreign_investor_buy_sell": -16747341,
        "investment_trust_buy_sell": 0,
        "dealer_self_buy_sell": 180000,
        "dealer_hedging_buy_sell": -25055328,
        "margin_date": "2026-06-29",
        "margin_today_balance": 74642,
        "margin_delta_estimated": -4107,
        "technical": {
          "pct_change_5d": -9.608091024020226,
          "pct_change_20d": -2.985074626865669,
          "high_60d": 23.73,
          "low_60d": 12.44,
          "pct_from_60d_high": -9.608091024020226,
          "pct_from_60d_low": 72.42765273311898
        },
        "freshness": {
          "price": "fresh",
          "institutional": "fresh",
          "margin": "fresh"
        }
      },
      "6005": {
        "name": "群益證",
        "price_date": "2026-06-29",
        "open": 38.3,
        "max": 38.35,
        "min": 37.5,
        "close": 37.55,
        "spread": -0.25,
        "trading_volume": 10065553,
        "institutional_date": "2026-06-29",
        "foreign_investor_buy_sell": 1761560,
        "investment_trust_buy_sell": -4640550,
        "dealer_self_buy_sell": 0,
        "dealer_hedging_buy_sell": 0,
        "margin_date": "2026-06-29",
        "margin_today_balance": 5264,
        "margin_delta_estimated": 73,
        "technical": {
          "pct_change_5d": -5.6532663316582905,
          "pct_change_20d": -2.467532467532474,
          "high_60d": 45.05,
          "low_60d": 27.6,
          "pct_from_60d_high": -16.648168701442845,
          "pct_from_60d_low": 36.05072463768116
        },
        "freshness": {
          "price": "fresh",
          "institutional": "fresh",
          "margin": "fresh"
        }
      }
    }
  },
  "us": {
    "source": "Yahoo Finance via yfinance",
    "mode": "us_intraday_or_latest_available",
    "tickers": {
      "SPY": {
        "date": "2026-06-29",
        "open": 736.5250244140625,
        "high": 739.885009765625,
        "low": 732.1099853515625,
        "close": 738.260009765625,
        "previous_close": 728.989990234375,
        "pct_change": 1.2716250779067018,
        "volume": 23733198.0,
        "intraday_or_latest_price": 738.260009765625,
        "intraday_vs_previous_close_pct": 1.2716250779067018,
        "technical": {
          "pct_change_5d": -0.8234937011759369,
          "pct_change_20d": -2.408519878058779,
          "high_52w": 760.4000244140625,
          "low_52w": 615.0399780273438,
          "pct_from_52w_high": -2.911627293212915,
          "pct_from_52w_low": 20.03447517891317
        },
        "freshness": "fresh"
      },
      "QQQ": {
        "date": "2026-06-29",
        "open": 713.989990234375,
        "high": 720.530029296875,
        "low": 705.1719970703125,
        "close": 719.5900268554688,
        "previous_close": 706.52001953125,
        "pct_change": 1.849913231459488,
        "volume": 23444273.0,
        "intraday_or_latest_price": 719.5900268554688,
        "intraday_vs_previous_close_pct": 1.849913231459488,
        "technical": {
          "pct_change_5d": -2.4879714137617803,
          "pct_change_20d": -2.535516350181799,
          "high_52w": 748.6500244140625,
          "low_52w": 544.6599731445312,
          "pct_from_52w_high": -3.8816531905328966,
          "pct_from_52w_low": 32.117295622257515
        },
        "freshness": "fresh"
      },
      "^IXIC": {
        "date": "2026-06-29",
        "open": 25502.087890625,
        "high": 25697.224609375,
        "low": 25289.763671875,
        "close": 25629.849609375,
        "previous_close": 25297.619140625,
        "pct_change": 1.3132874951717444,
        "volume": 4653160000.0,
        "intraday_or_latest_price": 25629.849609375,
        "intraday_vs_previous_close_pct": 1.3132874951717444,
        "technical": {
          "pct_change_5d": -2.0512791421614107,
          "pct_change_20d": -4.97826897806738,
          "high_52w": 27190.2109375,
          "low_52w": 20105.41015625,
          "pct_from_52w_high": -5.738687837735723,
          "pct_from_52w_low": 27.47737753267203
        },
        "freshness": "fresh"
      },
      "SOXX": {
        "date": "2026-06-29",
        "open": 593.7000122070312,
        "high": 608.97998046875,
        "low": 571.5999755859375,
        "close": 606.9299926757812,
        "previous_close": 589.9400024414062,
        "pct_change": 2.8799522263389,
        "volume": 6871013.0,
        "intraday_or_latest_price": 606.9299926757812,
        "intraday_vs_previous_close_pct": 2.8799522263389,
        "technical": {
          "pct_change_5d": -7.340348448575263,
          "pct_change_20d": 6.651081473479659,
          "high_52w": 655.9500122070312,
          "low_52w": 232.3300018310547,
          "pct_from_52w_high": -7.473133412455568,
          "pct_from_52w_low": 161.23616747402582
        },
        "freshness": "fresh"
      },
      "SMH": {
        "date": "2026-06-29",
        "open": 615.0599975585938,
        "high": 628.0,
        "low": 596.2901000976562,
        "close": 626.0999755859375,
        "previous_close": 611.6099853515625,
        "pct_change": 2.369155275652668,
        "volume": 6039730.0,
        "intraday_or_latest_price": 626.0999755859375,
        "intraday_vs_previous_close_pct": 2.369155275652668,
        "technical": {
          "pct_change_5d": -6.3999640126973905,
          "pct_change_20d": 4.536420490276605,
          "high_52w": 671.8300170898438,
          "low_52w": 272.1600036621094,
          "pct_from_52w_high": -6.806787482047083,
          "pct_from_52w_low": 130.0484888158841
        },
        "freshness": "fresh"
      },
      "^VIX": {
        "date": "2026-06-29",
        "open": 18.600000381469727,
        "high": 19.450000762939453,
        "low": 17.790000915527344,
        "close": 17.84000015258789,
        "previous_close": 18.40999984741211,
        "pct_change": -3.0961417683245895,
        "volume": 0.0,
        "intraday_or_latest_price": 17.84000015258789,
        "intraday_vs_previous_close_pct": -3.0961417683245895,
        "technical": {
          "pct_change_5d": 3.2407375213541867,
          "pct_change_20d": 16.44908947756076,
          "high_52w": 35.29999923706055,
          "low_52w": 13.380000114440918,
          "pct_from_52w_high": -49.46175484939348,
          "pct_from_52w_low": 33.33333333333333
        },
        "freshness": "fresh"
      },
      "NVDA": {
        "date": "2026-06-29",
        "open": 193.78500366210938,
        "high": 196.1699981689453,
        "low": 189.8000030517578,
        "close": 192.89999389648438,
        "previous_close": 192.52999877929688,
        "pct_change": 0.19217530750188505,
        "volume": 73621360.0,
        "intraday_or_latest_price": 192.89999389648438,
        "intraday_vs_previous_close_pct": 0.19217530750188505,
        "technical": {
          "pct_change_5d": -7.548526460927629,
          "pct_change_20d": -8.638820472620646,
          "high_52w": 236.5399932861328,
          "low_52w": 151.49000549316406,
          "pct_from_52w_high": -18.44931116441646,
          "pct_from_52w_low": 27.335128986571288
        },
        "freshness": "fresh"
      },
      "TSM": {
        "date": "2026-06-29",
        "open": 437.0,
        "high": 450.1300048828125,
        "low": 431.0899963378906,
        "close": 449.2900085449219,
        "previous_close": 432.3500061035156,
        "pct_change": 3.9181224013560945,
        "volume": 7667848.0,
        "intraday_or_latest_price": 449.2900085449219,
        "intraday_vs_previous_close_pct": 3.9181224013560945,
        "technical": {
          "pct_change_5d": -3.930122598217989,
          "pct_change_20d": 7.370055069476811,
          "high_52w": 476.7900085449219,
          "low_52w": 221.17999267578125,
          "pct_from_52w_high": -5.767738313964488,
          "pct_from_52w_low": 103.1332052730094
        },
        "freshness": "fresh"
      },
      "AVGO": {
        "date": "2026-06-29",
        "open": 373.5199890136719,
        "high": 375.2107849121094,
        "low": 360.4599914550781,
        "close": 370.1650085449219,
        "previous_close": 365.0199890136719,
        "pct_change": 1.4095172007298817,
        "volume": 9424581.0,
        "intraday_or_latest_price": 370.1650085449219,
        "intraday_vs_previous_close_pct": 1.4095172007298817,
        "technical": {
          "pct_change_5d": -5.6014576962695966,
          "pct_change_20d": -17.14640247834681,
          "high_52w": 495.0,
          "low_52w": 262.6600036621094,
          "pct_from_52w_high": -25.219190192945074,
          "pct_from_52w_low": 40.92933959641183
        },
        "freshness": "fresh"
      },
      "MSFT": {
        "date": "2026-06-29",
        "open": 377.5,
        "high": 380.5,
        "low": 367.6000061035156,
        "close": 367.80499267578125,
        "previous_close": 372.9700012207031,
        "pct_change": -1.3848321655943296,
        "volume": 23870451.0,
        "intraday_or_latest_price": 367.80499267578125,
        "intraday_vs_previous_close_pct": -1.3848321655943296,
        "technical": {
          "pct_change_5d": 0.12658472873259274,
          "pct_change_20d": -18.309123877619516,
          "high_52w": 555.4500122070312,
          "low_52w": 349.20001220703125,
          "pct_from_52w_high": -33.78252145240923,
          "pct_from_52w_low": 5.327886545925886
        },
        "freshness": "fresh"
      },
      "GOOGL": {
        "date": "2026-06-29",
        "open": 341.82501220703125,
        "high": 352.7650146484375,
        "low": 340.6700134277344,
        "close": 351.7820129394531,
        "previous_close": 337.3900146484375,
        "pct_change": 4.265685902415384,
        "volume": 16808682.0,
        "intraday_or_latest_price": 351.7820129394531,
        "intraday_vs_previous_close_pct": 4.265685902415384,
        "technical": {
          "pct_change_5d": 0.60112683244673,
          "pct_change_20d": -7.508540693434417,
          "high_52w": 408.6099853515625,
          "low_52w": 172.77000427246094,
          "pct_from_52w_high": -13.907631837047585,
          "pct_from_52w_low": 103.61289821159438
        },
        "freshness": "fresh"
      },
      "META": {
        "date": "2026-06-29",
        "open": 560.0,
        "high": 570.9000244140625,
        "low": 558.0,
        "close": 564.0700073242188,
        "previous_close": 550.25,
        "pct_change": 2.5115869739607,
        "volume": 6749582.0,
        "intraday_or_latest_price": 564.0700073242188,
        "intraday_vs_previous_close_pct": 2.5115869739607,
        "technical": {
          "pct_change_5d": 0.03902309972658724,
          "pct_change_20d": -10.820382505371972,
          "high_52w": 796.25,
          "low_52w": 520.260009765625,
          "pct_from_52w_high": -29.159182753630297,
          "pct_from_52w_low": 8.420788977867044
        },
        "freshness": "fresh"
      },
      "AMZN": {
        "date": "2026-06-29",
        "open": 234.2449951171875,
        "high": 249.7100067138672,
        "low": 233.8000030517578,
        "close": 239.9499969482422,
        "previous_close": 232.69000244140625,
        "pct_change": 3.120028548997955,
        "volume": 41157248.0,
        "intraday_or_latest_price": 239.9499969482422,
        "intraday_vs_previous_close_pct": 3.120028548997955,
        "technical": {
          "pct_change_5d": 3.075735155552284,
          "pct_change_20d": -11.339793097506945,
          "high_52w": 278.55999755859375,
          "low_52w": 196.0,
          "pct_from_52w_high": -13.860568979302258,
          "pct_from_52w_low": 22.42346783073581
        },
        "freshness": "fresh"
      },
      "AMBA": {
        "date": "2026-06-29",
        "open": 62.90999984741211,
        "high": 64.80989837646484,
        "low": 60.34000015258789,
        "close": 64.4000015258789,
        "previous_close": 62.130001068115234,
        "pct_change": 3.653630160532262,
        "volume": 559332.0,
        "intraday_or_latest_price": 64.4000015258789,
        "intraday_vs_previous_close_pct": 3.653630160532262,
        "technical": {
          "pct_change_5d": -8.923769820807948,
          "pct_change_20d": -10.778607296208332,
          "high_52w": 96.69000244140625,
          "low_52w": 48.29999923706055,
          "pct_from_52w_high": -33.395387423942765,
          "pct_from_52w_low": 33.333338598616045
        },
        "freshness": "fresh"
      }
    }
  }
}