{
  "schema_version": "market-data-v2",
  "generated_at": "2026-07-25 06:50:18 CST",
  "generated_timezone": "Asia/Taipei",
  "market_mode": "full",
  "privacy_note": "This file contains market data only. No personal holdings, cash, target allocation, or buy/sell recommendations are included.",
  "taiwan": {
    "source": "FinMind",
    "mode": "tw_intraday_or_latest_available",
    "lookback_start": "2026-04-26",
    "lookback_end": "2026-07-25",
    "market_margin": {
      "date": "2026-07-24",
      "today_balance": 577059537000,
      "yesterday_balance": 582626349000,
      "delta": -5566812000,
      "freshness": "fresh"
    },
    "stocks": {
      "0050": {
        "name": "元大台灣50",
        "price_date": "2026-07-24",
        "open": 102.55,
        "max": 103.05,
        "min": 101.3,
        "close": 101.7,
        "spread": -2.2,
        "trading_volume": 105138918,
        "institutional_date": "2026-07-24",
        "foreign_investor_buy_sell": -37393633,
        "investment_trust_buy_sell": 1000000,
        "dealer_self_buy_sell": 5874426,
        "dealer_hedging_buy_sell": -5754856,
        "margin_date": "2026-07-24",
        "margin_today_balance": 32467,
        "margin_delta_estimated": -16323,
        "technical": {
          "pct_change_5d": 1.5476784822765932,
          "pct_change_20d": -5.1305970149253755,
          "high_60d": 111.15,
          "low_60d": 90.5,
          "pct_from_60d_high": -8.502024291497978,
          "pct_from_60d_low": 12.375690607734802
        },
        "freshness": {
          "price": "fresh",
          "institutional": "fresh",
          "margin": "fresh"
        }
      },
      "00988A": {
        "name": "主動統一台股增長",
        "price_date": "2026-07-24",
        "open": 17.48,
        "max": 17.53,
        "min": 17.1,
        "close": 17.22,
        "spread": -0.64,
        "trading_volume": 40104828,
        "institutional_date": "2026-07-24",
        "foreign_investor_buy_sell": -4859261,
        "investment_trust_buy_sell": 0,
        "dealer_self_buy_sell": 0,
        "dealer_hedging_buy_sell": -4499950,
        "margin_date": "2026-07-24",
        "margin_today_balance": 71345,
        "margin_delta_estimated": -1019,
        "technical": {
          "pct_change_5d": 6.034482758620685,
          "pct_change_20d": -25.35760728218466,
          "high_60d": 23.73,
          "low_60d": 16.24,
          "pct_from_60d_high": -27.43362831858408,
          "pct_from_60d_low": 6.034482758620685
        },
        "freshness": {
          "price": "fresh",
          "institutional": "fresh",
          "margin": "fresh"
        }
      },
      "6005": {
        "name": "群益證",
        "price_date": "2026-07-24",
        "open": 34.35,
        "max": 35.05,
        "min": 34.25,
        "close": 34.8,
        "spread": 0.35,
        "trading_volume": 6712949,
        "institutional_date": "2026-07-24",
        "foreign_investor_buy_sell": 190002,
        "investment_trust_buy_sell": 16000,
        "dealer_self_buy_sell": 0,
        "dealer_hedging_buy_sell": 0,
        "margin_date": "2026-07-24",
        "margin_today_balance": 5235,
        "margin_delta_estimated": 83,
        "technical": {
          "pct_change_5d": 5.454545454545445,
          "pct_change_20d": -10.309278350515461,
          "high_60d": 45.05,
          "low_60d": 28.05,
          "pct_from_60d_high": -22.752497225305213,
          "pct_from_60d_low": 24.064171122994637
        },
        "freshness": {
          "price": "fresh",
          "institutional": "fresh",
          "margin": "fresh"
        }
      }
    }
  },
  "us": {
    "source": "Yahoo Finance via yfinance",
    "mode": "us_intraday_or_latest_available",
    "tickers": {
      "SPY": {
        "date": "2026-07-24",
        "open": 738.510009765625,
        "high": 743.719970703125,
        "low": 737.2899780273438,
        "close": 738.9299926757812,
        "previous_close": 738.1799926757812,
        "pct_change": 0.10160123647910968,
        "volume": 41480799.0,
        "intraday_or_latest_price": 738.9299926757812,
        "intraday_vs_previous_close_pct": 0.10160123647910968,
        "technical": {
          "pct_change_5d": -0.5865793271064512,
          "pct_change_20d": 0.630533155356372,
          "high_52w": 760.4000244140625,
          "low_52w": 619.2899780273438,
          "pct_from_52w_high": -2.8235180232700885,
          "pct_from_52w_low": 19.318900497878722
        },
        "freshness": "fresh"
      },
      "QQQ": {
        "date": "2026-07-24",
        "open": 690.25,
        "high": 692.6300048828125,
        "low": 682.47998046875,
        "close": 684.22998046875,
        "previous_close": 691.9600219726562,
        "pct_change": -1.1171225588826994,
        "volume": 39636030.0,
        "intraday_or_latest_price": 684.22998046875,
        "intraday_vs_previous_close_pct": -1.1171225588826994,
        "technical": {
          "pct_change_5d": -1.596369543709708,
          "pct_change_20d": -4.487845025674842,
          "high_52w": 748.6500244140625,
          "low_52w": 551.6799926757812,
          "pct_from_52w_high": -8.60482760228739,
          "pct_from_52w_low": 24.02660773505112
        },
        "freshness": "fresh"
      },
      "^IXIC": {
        "date": "2026-07-24",
        "open": 25107.3828125,
        "high": 25222.138671875,
        "low": 24918.09375,
        "close": 24975.82421875,
        "previous_close": 25137.689453125,
        "pct_change": -0.6439145279315994,
        "volume": 6271768000.0,
        "intraday_or_latest_price": 24975.82421875,
        "intraday_vs_previous_close_pct": -0.6439145279315994,
        "technical": {
          "pct_change_5d": -2.1332715155701676,
          "pct_change_20d": -1.5094500347861861,
          "high_52w": 27190.2109375,
          "low_52w": 20560.169921875,
          "pct_from_52w_high": -8.144058624039497,
          "pct_from_52w_low": 21.476740287914463
        },
        "freshness": "fresh"
      },
      "SOXX": {
        "date": "2026-07-24",
        "open": 544.7100219726562,
        "high": 548.0,
        "low": 522.219970703125,
        "close": 527.010009765625,
        "previous_close": 551.239990234375,
        "pct_change": -4.395541125100144,
        "volume": 10500488.0,
        "intraday_or_latest_price": 527.010009765625,
        "intraday_vs_previous_close_pct": -4.395541125100144,
        "technical": {
          "pct_change_5d": 0.9965336485235454,
          "pct_change_20d": -15.705374364082903,
          "high_52w": 655.9500122070312,
          "low_52w": 232.3300018310547,
          "pct_from_52w_high": -19.65698605714945,
          "pct_from_52w_low": 126.83682934279629
        },
        "freshness": "fresh"
      },
      "SMH": {
        "date": "2026-07-24",
        "open": 574.9199829101562,
        "high": 578.52001953125,
        "low": 556.489990234375,
        "close": 561.1900024414062,
        "previous_close": 580.1699829101562,
        "pct_change": -3.271451648281709,
        "volume": 18909935.0,
        "intraday_or_latest_price": 561.1900024414062,
        "intraday_vs_previous_close_pct": -3.271451648281709,
        "technical": {
          "pct_change_5d": 0.8373264512642198,
          "pct_change_20d": -11.884499726967157,
          "high_52w": 671.8300170898438,
          "low_52w": 279.19000244140625,
          "pct_from_52w_high": -16.46845360195355,
          "pct_from_52w_low": 101.00648215696171
        },
        "freshness": "fresh"
      },
      "^VIX": {
        "date": "2026-07-24",
        "open": 18.959999084472656,
        "high": 19.049999237060547,
        "low": 17.40999984741211,
        "close": 18.579999923706055,
        "previous_close": 18.700000762939453,
        "pct_change": -0.6417156916443623,
        "volume": 0.0,
        "intraday_or_latest_price": 18.579999923706055,
        "intraday_vs_previous_close_pct": -0.6417156916443623,
        "technical": {
          "pct_change_5d": -1.0122564167494685,
          "pct_change_20d": -1.641077162301341,
          "high_52w": 35.29999923706055,
          "low_52w": 13.380000114440918,
          "pct_from_52w_high": -47.36543817202297,
          "pct_from_52w_low": 38.863974325776155
        },
        "freshness": "fresh"
      },
      "NVDA": {
        "date": "2026-07-24",
        "open": 207.55999755859375,
        "high": 211.90989685058594,
        "low": 204.80999755859375,
        "close": 206.83999633789062,
        "previous_close": 208.75999450683594,
        "pct_change": -0.9197155678610791,
        "volume": 110844026.0,
        "intraday_or_latest_price": 206.83999633789062,
        "intraday_vs_previous_close_pct": -0.9197155678610791,
        "technical": {
          "pct_change_5d": 1.9870809268821121,
          "pct_change_20d": 5.670782943302921,
          "high_52w": 236.5399932861328,
          "low_52w": 164.07000732421875,
          "pct_from_52w_high": -12.556014962051387,
          "pct_from_52w_low": 26.06813378703281
        },
        "freshness": "fresh"
      },
      "TSM": {
        "date": "2026-07-24",
        "open": 411.3450012207031,
        "high": 412.8800048828125,
        "low": 400.80010986328125,
        "close": 403.4100036621094,
        "previous_close": 415.5799865722656,
        "pct_change": -2.928433346979764,
        "volume": 11485132.0,
        "intraday_or_latest_price": 403.4100036621094,
        "intraday_vs_previous_close_pct": -2.928433346979764,
        "technical": {
          "pct_change_5d": 1.2651576691761868,
          "pct_change_20d": -7.25993408612694,
          "high_52w": 479.0,
          "low_52w": 223.6999969482422,
          "pct_from_52w_high": -15.780792554883217,
          "pct_from_52w_low": 80.33527454872831
        },
        "freshness": "fresh"
      },
      "AVGO": {
        "date": "2026-07-24",
        "open": 387.92498779296875,
        "high": 389.2699890136719,
        "low": 378.75,
        "close": 381.9200134277344,
        "previous_close": 392.4700012207031,
        "pct_change": -2.688100430645657,
        "volume": 13948973.0,
        "intraday_or_latest_price": 381.9200134277344,
        "intraday_vs_previous_close_pct": -2.688100430645657,
        "technical": {
          "pct_change_5d": 2.990596029727377,
          "pct_change_20d": 0.7943864602501183,
          "high_52w": 495.0,
          "low_52w": 281.6099853515625,
          "pct_from_52w_high": -22.844441731770836,
          "pct_from_52w_low": 35.620195765055925
        },
        "freshness": "fresh"
      },
      "MSFT": {
        "date": "2026-07-24",
        "open": 387.04998779296875,
        "high": 389.0299987792969,
        "low": 380.6499938964844,
        "close": 381.70001220703125,
        "previous_close": 381.5799865722656,
        "pct_change": 0.03145490827332065,
        "volume": 27544509.0,
        "intraday_or_latest_price": 381.70001220703125,
        "intraday_vs_previous_close_pct": 0.03145490827332065,
        "technical": {
          "pct_change_5d": -3.077546821334931,
          "pct_change_20d": 8.182418369605493,
          "high_52w": 555.4500122070312,
          "low_52w": 349.20001220703125,
          "pct_from_52w_high": -31.28094269178604,
          "pct_from_52w_low": 9.3069870744253
        },
        "freshness": "fresh"
      },
      "GOOGL": {
        "date": "2026-07-24",
        "open": 318.31500244140625,
        "high": 324.17999267578125,
        "low": 317.3299865722656,
        "close": 319.739990234375,
        "previous_close": 317.69000244140625,
        "pct_change": 0.6452792902561733,
        "volume": 31306769.0,
        "intraday_or_latest_price": 319.739990234375,
        "intraday_vs_previous_close_pct": 0.6452792902561733,
        "technical": {
          "pct_change_5d": -7.794791831951519,
          "pct_change_20d": -6.973902946267985,
          "high_52w": 408.6099853515625,
          "low_52w": 187.82000732421875,
          "pct_from_52w_high": -21.749344926244262,
          "pct_from_52w_low": 70.23744956118188
        },
        "freshness": "fresh"
      },
      "META": {
        "date": "2026-07-24",
        "open": 605.3400268554688,
        "high": 609.97998046875,
        "low": 594.5999755859375,
        "close": 595.1900024414062,
        "previous_close": 606.0999755859375,
        "pct_change": -1.8000286394970089,
        "volume": 11309789.0,
        "intraday_or_latest_price": 595.1900024414062,
        "intraday_vs_previous_close_pct": -1.8000286394970089,
        "technical": {
          "pct_change_5d": -7.866752303521807,
          "pct_change_20d": 9.637667912171977,
          "high_52w": 796.25,
          "low_52w": 520.260009765625,
          "pct_from_52w_high": -25.250863115678968,
          "pct_from_52w_low": 14.402412499384099
        },
        "freshness": "fresh"
      },
      "AMZN": {
        "date": "2026-07-24",
        "open": 234.3699951171875,
        "high": 234.9499969482422,
        "low": 231.35000610351562,
        "close": 232.11000061035156,
        "previous_close": 233.66000366210938,
        "pct_change": -0.6633583101364859,
        "volume": 33836532.0,
        "intraday_or_latest_price": 232.11000061035156,
        "intraday_vs_previous_close_pct": -0.6633583101364859,
        "technical": {
          "pct_change_5d": -6.115760780844148,
          "pct_change_20d": 2.2465998092264794,
          "high_52w": 278.55999755859375,
          "low_52w": 196.0,
          "pct_from_52w_high": -16.675042129289096,
          "pct_from_52w_low": 18.423469699158957
        },
        "freshness": "fresh"
      },
      "AMBA": {
        "date": "2026-07-24",
        "open": 68.44000244140625,
        "high": 69.27999877929688,
        "low": 66.5999984741211,
        "close": 68.05999755859375,
        "previous_close": 70.51000213623047,
        "pct_change": -3.474690828831817,
        "volume": 1346619.0,
        "intraday_or_latest_price": 68.05999755859375,
        "intraday_vs_previous_close_pct": -3.474690828831817,
        "technical": {
          "pct_change_5d": 10.058210528231326,
          "pct_change_20d": 6.161280472058528,
          "high_52w": 96.69000244140625,
          "low_52w": 48.29999923706055,
          "pct_from_52w_high": -29.61009841752995,
          "pct_from_52w_low": 40.91097025602306
        },
        "freshness": "fresh"
      }
    }
  }
}